LICENSE-umich-spanishwords-00readme.txt
LICENSE.BSD
MANIFEST.in
README.rst
setup.py
xkcdpass.1
examples/example_import.py
examples/example_json.py
examples/example_postprocess.py
tests/__init__.py
tests/test_list.txt
tests/test_xkcdpass.py
xkcdpass/__init__.py
xkcdpass/__main__.py
xkcdpass/xkcd_password.py
xkcdpass.egg-info/PKG-INFO
xkcdpass.egg-info/SOURCES.txt
xkcdpass.egg-info/dependency_links.txt
xkcdpass.egg-info/entry_points.txt
xkcdpass.egg-info/not-zip-safe
xkcdpass.egg-info/top_level.txt
xkcdpass/static/eff-long
xkcdpass/static/eff-short
xkcdpass/static/eff-special
xkcdpass/static/eff_large_de_sample.wordlist
xkcdpass/static/fin-kotus
xkcdpass/static/fr-corrected.txt
xkcdpass/static/fr-freelang
xkcdpass/static/ger-anlx
xkcdpass/static/ger-long
xkcdpass/static/ger-short
xkcdpass/static/ita-wiki
xkcdpass/static/legacy
xkcdpass/static/nor-nb
xkcdpass/static/pt-ipublicis
xkcdpass/static/pt-l33t-ipublicis
xkcdpass/static/spa-mich
xkcdpass/static/swe-short