Metadata-Version: 2.1
Name: xkcdpass
Version: 1.20.0
Summary: Generate secure multiword passwords/passphrases, inspired by XKCD
Home-page: https://github.com/redacted/XKCD-password-generator
Author: Steven Tobin
Author-email: steventtobin@gmail.com
License: BSD
Classifier: Development Status :: 5 - Production/Stable
Classifier: Programming Language :: Python :: 2
Classifier: Programming Language :: Python :: 2.7
Classifier: Programming Language :: Python :: 3
Classifier: Programming Language :: Python :: 3.4
Classifier: Programming Language :: Python :: 3.5
Classifier: Programming Language :: Python :: 3.6
Classifier: Programming Language :: Python :: 3.7
Classifier: Programming Language :: Python :: 3.8
Classifier: Programming Language :: Python :: 3.9
Classifier: Environment :: Console
Classifier: Operating System :: OS Independent
Classifier: License :: OSI Approved :: BSD License
License-File: LICENSE-umich-spanishwords-00readme.txt
License-File: LICENSE.BSD
